ihsginfocli.py
ihsginfo_cli-0.0.4.dist-info/LICENSE
ihsginfo_cli-0.0.4.dist-info/METADATA
ihsginfo_cli-0.0.4.dist-info/WHEEL
ihsginfo_cli-0.0.4.dist-info/entry_points.txt
ihsginfo_cli-0.0.4.dist-info/top_level.txt
ihsginfo_cli-0.0.4.dist-info/RECORD
